latlonheightReader/__init__.py
latlonheightReader/utils.py
latlonheightReader-1.0.1.dist-info/LICENSE
latlonheightReader-1.0.1.dist-info/METADATA
latlonheightReader-1.0.1.dist-info/WHEEL
latlonheightReader-1.0.1.dist-info/top_level.txt
latlonheightReader-1.0.1.dist-info/RECORD
